[{"type":"farm","street":"1305 N. Smith Rd.","city":"Palmer","state":"ak","zip":"99645","x":"-149.025325","y":"61.593207","name":"Arctic Organics","website":"Arctic Organics.com","facebook":"","twitter":"","tags":"fresh-fruits fresh-vegetables"},{"type":"farm","street":"12th & Main st. ","city":"Skagway ","state":"ak","zip":"99840","x":"-135.310728","y":"59.460729","name":"Magpie Mini-farm","website":"https://magpie-103280.square.site/","facebook":"https://www.facebook.com/Magpie.etcetera","twitter":"","tags":"baked-goods bedding plants canned preserved crafts woodworking cut-flowers herbs fresh-fruits fresh-vegetables"},{"type":"farm","street":"19045 Darby Road","city":"Eagle River","state":"ak","zip":"99577","x":"-149.527083","y":"61.360154","name":"Monastery Acres","website":"","facebook":"","twitter":"","tags":"bedding plants canned preserved herbs fresh-fruits fresh-vegetables juices ciders soap body-care"},{"type":"farm","street":"73 Brown Rd","city":"Phenix City","state":"ak","zip":"36869","x":"-85.182649","y":"32.447297","name":"Serenity Farm","website":"http://thinkserenity.com","facebook":"https://www.facebook.com/AlabamaSerenityFarm/","twitter":"","tags":""},{"type":"farm","street":"6400 Baseline","city":"Fairbanks","state":"ak","zip":"99712","x":"-146.976997","y":"64.867087","name":"White Fireweed Farm","website":"","facebook":"https://www.facebook.com/whitefireweedfarm","twitter":"","tags":""},{"type":"market","name":"Farmers Fresh Market","website":"","facebook":"https://www.facebook.com/FarmersFreshMarketAK/","twitter":"","street":"33955 Community College Dr.","city":"Soldotna","state":"ak","zip":"99669","x":"-151.135361","y":"60.472775","tags":"baked goods flowers eggs vegetables honey jams plants trees coffee fruits mushrooms"},{"type":"market","name":"Homer Farmers Market","website":"http://www.homerfarmersmarket.org","facebook":"https://www.facebook.com/homerakfarmersmarket/","twitter":"","street":"Ocean Drive","city":"Homer","state":"ak","zip":"99603","x":"-151.512342","y":"59.638109","tags":"baked goods crafts flowers eggs seafood herbs vegetables honey jams plants poultry prepared-foods soap trees coffee fruits grains juices mushrooms pet food wild"},{"type":"market","name":"Juneau Farmers Market and Local Food Festival ","website":"https://jahc.org/food-festival/","facebook":"facebook/juneau.arts","twitter":"","street":"350 Whittier","city":"Juneau","state":"ak","zip":"99801","x":"-134.4136031","y":"58.2998500","tags":"organic baked goods crafts flowers seafood herbs vegetables jams plants prepared-foods soap trees coffee fruits mushrooms pet food wild"},{"type":"market","name":"Muldoon Farmers Market","website":"http://muldoonfarmersmarket.org","facebook":"http://www.facebook.com/muldoonfarmersmarket","twitter":"http://twitter.com/MuldoonFarmers","street":"1301 Muldoon Road","city":"Anchorage","state":"ak","zip":"99504","x":"-149.7311890","y":"61.2089910","tags":"baked goods crafts flowers eggs seafood herbs vegetables honey jams plants prepared-foods soap coffee fruits"},{"type":"market","name":"My Matanuska Marketplace","website":"https://www.facebook.com/MyMatanuskaMarketplace/?ref=bookmarks","facebook":"https://www.facebook.com/MyMatanuskaMarketplace/?ref=bookmarks","twitter":"","street":"610 S Valley Way","city":"Palmer","state":"ak","zip":"99645","x":"-149.113628","y":"61.599930","tags":"organic baked goods cheese crafts flowers eggs seafood herbs vegetables honey jams plants soap coffee fruits"},{"type":"market","name":"Sitka Farmers Market","website":"http://www.sitkalocalfoodsnetwork.org/","facebook":"www.facebook.com/SitkaLocalFoodsNetwork","twitter":"@SitkaLocalFoods","street":"611 Lincoln Street","city":"Sitka","state":"ak","zip":"99835","x":"-135.326742","y":"57.051519","tags":"flowers herbs vegetables fruits"},{"type":"market","name":"Soldotna Saturday Farmers Market","website":"http://soldotnasaturdayfarmersmarket.com","facebook":"Facebook.com/soldotnasaturdayfarmersmarket","twitter":"@Soldotnam","street":"193 E. Corral Ave","city":"Soldotna","state":"ak","zip":"99669","x":"-151.067584","y":"60.493040","tags":"baked goods crafts flowers eggs seafood herbs vegetables honey jams poultry prepared-foods soap coffee mushrooms wild"},{"type":"market","name":"The Market in Petersburg, Alaska","website":"","facebook":"facebook.com/petersburgmarket","twitter":"","street":"1st and Gjoa","city":"Petersburg, AK","state":"ak","zip":"99833","x":"-132.955913","y":"56.811930","tags":"baked goods flowers seafood vegetables jams prepared-foods soap coffee wild"}]
