[{"type":"farm","street":"158 N 4544 E","city":"Rigby","state":"id","zip":"83442","x":"-111.7958160","y":"43.6501639","name":"Ashland Produce","website":"","facebook":"","twitter":"","tags":"fresh-fruits fresh-vegetables"},{"type":"farm","street":"14623 Galloway Rd","city":"Caldwell","state":"id","zip":"83607","x":"-116.683530","y":"43.749677","name":"Black Dog Berry Farm and Market Garden","website":"","facebook":"","twitter":"","tags":"cut-flowers eggs herbs fresh-fruits fresh-vegetables"},{"type":"farm","street":"3525 E. Virginia Road","city":"Downey","state":"id","zip":"83234","x":"-112.1586133","y":"42.5034199","name":"Bradys Plant Ranch","website":"www.bradysplantranch.com","facebook":"","twitter":"","tags":"baked-goods bedding plants canned preserved crafts woodworking dairy products eggs herbs fresh-fruits fresh-vegetables honey juices ciders nursery-stock prepared-foods red-meat non-poultry-meat"},{"type":"farm","street":"2087 West King Rd","city":"Kuna","state":"id","zip":"83634","x":"-116.439328","y":"43.473453","name":"Cabalo's Orchard & Gardens","website":"cabalosorchard.com","facebook":"https://www.facebook.com/Aplles4uall","twitter":"","tags":"eggs fresh-fruits fresh-vegetables honey juices ciders poultry fowl"},{"type":"farm","street":"147 ELLSWORTH RD","city":"POCATELLO","state":"id","zip":"83202","x":"-112.462140","y":"43.022498","name":"Giving Ground Farm","website":"www.givinggroundseeds.com","facebook":"","twitter":"","tags":"cut-flowers dry beans herbs fresh-vegetables nursery-stock"},{"type":"farm","street":"Kuna Rd/cloverdale Area","city":"Kuna","state":"id","zip":"83634","x":"-116.4201223","y":"43.4918307","name":"Goshen Farm, LLC","website":"www.goshenfarm.weebly.com","facebook":"https://www.facebook.com/goshenfarm","twitter":"","tags":"dairy products"},{"type":"farm","street":"246 Wet 200 North","city":"Blackfoot","state":"id","zip":"83221","x":"-112.345567","y":"43.225728","name":"Grove City Gardens, LLC","website":"","facebook":"https://www.facebook.com/GroveCityGardens?ref_type=bookmark","twitter":"https://twitter.com/grovecitygarden","tags":""},{"type":"farm","street":"2190 W Burns Street","city":"Eagle","state":"id","zip":"83616","x":"-116.3805630","y":"43.7092380","name":"July Blueberries LLC.","website":"","facebook":"","twitter":"","tags":"fresh-fruits"},{"type":"farm","street":"53 Hill Road","city":"Weiser","state":"id","zip":"83672","x":"-116.877558","y":"44.159926","name":"Kelley Orchards","website":"www.kelleyorchards.com","facebook":"https://www.facebook.com/KelleyOrchards","twitter":"https://www.twitter.com/KelleyOrchards","tags":"canned preserved fresh-fruits fresh-vegetables honey"},{"type":"farm","street":"675 east highway 30","city":"Soda Springs","state":"id","zip":"83276","x":"-111.579731","y":"42.651939","name":"Lau Family Farm, llc","website":"www.laufamilyfarm.com","facebook":"https://www.facebook.com/laufamilyfarm/","twitter":"","tags":"red-meat non-poultry-meat"},{"type":"farm","street":"7 Mac Nab Lane","city":"Carmen","state":"id","zip":"83462","x":"-113.892029","y":"45.258484","name":"Mountain Valley Farmstead","website":"MountainValleyFarmstead.com","facebook":"https://www.facebook.com/mountainvalleyfarmstead/","twitter":"","tags":"dairy products"},{"type":"farm","street":"2 Scott Lane","city":"Salmon","state":"id","zip":"83467","x":"-113.798368","y":"45.130416","name":"Mundy Farms","website":"","facebook":"","twitter":"","tags":"crafts woodworking fresh-vegetables"},{"type":"farm","street":"1826 E  4500 N","city":"Buhl ","state":"id","zip":"83316","x":"-114.6870020","y":"42.6568320","name":"NORTHVIEW ORCHARD","website":"","facebook":"NORTHVIEW ORCHARD","twitter":"","tags":"fresh-fruits nuts"},{"type":"farm","street":"660 South State Street","city":"Preston","state":"id","zip":"83263","x":"-111.8766600","y":"42.0842998","name":"Preston Berry Farms","website":"Prestonberryfarms@live.com","facebook":"https://www.facebook.com/pages/Preston-Berry-Farms/282551275111518","twitter":"","tags":"canned preserved fresh-fruits fresh-vegetables juices ciders"},{"type":"farm","street":"28405 W. Highway 53","city":"Hauser","state":"id","zip":"83854","x":"-117.036141","y":"47.739601","name":"Red Canoe Farms","website":"","facebook":"https://www.facebook.com/Redcanoefarms","twitter":"","tags":""},{"type":"farm","street":"4250 Valley View Road","city":"Emmett","state":"id","zip":"83617","x":"-116.677997","y":"43.870432","name":"Richardson Farm","website":"http://www.idahoberry.wordpress.com/","facebook":"https://www.facebook.com/idahoberry","twitter":"","tags":"fresh-fruits fresh-vegetables wine spirits beer hard-cider"},{"type":"farm","street":"2955 West South Slope Road","city":"Emmett","state":"id","zip":"83617","x":"-116.5663479","y":"43.8350104","name":"Wee Kings Orchard","website":"","facebook":"","twitter":"","tags":"eggs fresh-fruits"},{"type":"market","name":"Boise Farmers Market","website":"http://WWW.THEBOISEFARMERSMARKET.COM","facebook":"BOISE FARMERS MARKET","twitter":"BOISE FARMERS MARKET","street":"10TH & GROVE  - SUMMER MARKET","city":"Boise City","state":"id","zip":"83702","x":"-116.444084","y":"43.532957","tags":"organic baked goods cheese flowers eggs seafood herbs vegetables honey jams meat nuts plants poultry prepared-foods soap wine coffee fruits grains juices mushrooms wild"},{"type":"market","name":"BOISE FARMERS MARKET","website":"http://www.theboisefarmersmarket.com","facebook":"BOISE FARMERS MARKET","twitter":"BOISE FARMERS MARKET","street":"516 S. 8th Street","city":"Boise City","state":"id","zip":"83702","x":"-116.191930","y":"43.607980","tags":"organic baked goods cheese crafts eggs seafood herbs vegetables honey jams maple meat nuts poultry prepared-foods soap coffee beans fruits grains juices mushrooms wild"},{"type":"market","name":"Challis Community Farmers Market","website":"","facebook":"","twitter":"","street":"Challis City Park","city":"Challis ","state":"id","zip":"83226","x":"-114.227231","y":"44.505154","tags":"baked goods cheese crafts flowers eggs seafood herbs vegetables honey plants prepared-foods soap trees coffee fruits grains wild"},{"type":"market","name":"Donnelly Farmers Market","website":"","facebook":"donnelly farmers market","twitter":"","street":"FW Gestrin and E. Roseberry Rd","city":"donnelly","state":"id","zip":"83615","x":"-116.076720","y":"44.730034","tags":"organic baked goods crafts eggs herbs vegetables honey jams poultry soap coffee fruits"},{"type":"market","name":"Idaho Falls Farmers' Market","website":"http://www.idahofallsfarmersmarket.org/","facebook":"https://www.facebook.com/pages/Idaho-Falls-Farmers-Market/83193557893","twitter":"","street":"A - D St. Memorial Drive","city":"Idaho Falls","state":"id","zip":"83402","x":"-112.042508","y":"43.494592","tags":"baked goods cheese crafts flowers eggs herbs vegetables honey jams maple meat plants prepared-foods soap trees coffee fruits grains juices"},{"type":"market","name":"Meridian Main Street Market","website":"http://www.meridianmainstreetmarket.com","facebook":"https://www.facebook.com/MeridianMainStreetMarket/","twitter":"","street":"33 E. Broadway Ave.","city":"Meridian","state":"id","zip":"83642","x":"-116.392301","y":"43.609999","tags":"baked goods crafts flowers eggs vegetables honey jams meat poultry prepared-foods soap wine coffee grains pet food"},{"type":"market","name":"Moscow Farmers Market","website":"http://www.ci.moscow.id.us/197/Farmers-Market","facebook":"https://www.facebook.com/MoscowFarmersMarket/","twitter":"https://twitter.com/mosfarmersmkt","street":"400 South Main, Moscow, Idaho 83843","city":"Moscow","state":"id","zip":"83843","x":"-117.0014061","y":"46.7317086","tags":"organic baked goods cheese crafts flowers eggs herbs vegetables honey jams meat nuts plants poultry prepared-foods soap trees wine fruits grains juices mushrooms pet food wild"},{"type":"market","name":"Orofino Farmers Market","website":"http://www.orofinofarmersmarket.com/","facebook":"https://www.facebook.com/Orofino-Farmers-Market-139500116131731/","twitter":"","street":"101 Michigan Ave.","city":"Orofino","state":"id","zip":"83544","x":"-116.255806","y":"46.477929","tags":"baked goods cheese crafts flowers eggs herbs vegetables honey jams meat nuts plants prepared-foods soap fruits"},{"type":"market","name":"Payette Farmers Market","website":"http://www.payettevalleyfoodconnection.com","facebook":"www.facebook.com/payettefarmersmarket/","twitter":"","street":"Kiwanis Park","city":"Payette ","state":"id","zip":"83661","x":"-116.935907","y":"44.069117","tags":"baked goods crafts vegetables fruits"},{"type":"market","name":"Rexburg Farmers Market","website":"http://www.rexburgfarmersmarket.org/","facebook":"https://www.facebook.com/rexburgfarmersmarket/","twitter":"https://twitter.com/RexburgMarket","street":"118 College Ave.","city":"Rexburg","state":"id","zip":"83440","x":"-111.782405","y":"43.823218","tags":"baked goods crafts flowers eggs herbs vegetables honey jams plants prepared-foods soap fruits grains"},{"type":"market","name":"Silver Valley Farmers Market","website":"http://www.silvervalleychamber.com/farmers-market.htm","facebook":"https://business.facebook.com/silvervalleymarket/?business_id=522814814564925","twitter":"","street":"10 Station Ave","city":"Kellogg","state":"id","zip":"83837","x":"-116.120504","y":"47.536412","tags":"baked goods cheese crafts flowers eggs vegetables prepared-foods soap wine coffee fruits juices"},{"type":"market","name":"St. Maries Farmers Market","website":"","facebook":"https://www.facebook.com/stmariesfarmersmarkets/","twitter":"","street":"","city":"St. Maries","state":"id","zip":"83861","x":"-116.586445","y":"47.318286","tags":"baked goods crafts flowers eggs vegetables honey jams plants soap coffee fruits wild"},{"type":"market","name":"Weiser Farmer's Market","website":"","facebook":"Weiser Farmers Market","twitter":"","street":"1 State Street","city":"Weiser ","state":"id","zip":"83672","x":"-116.971130","y":"44.244083","tags":"baked goods crafts eggs herbs vegetables honey jams prepared-foods soap fruits"}]
