[{"type":"farm","street":"850 South Breeze","city":"St. Charles","state":"mo","zip":"63304","x":"-90.658483","y":"38.718752","name":"Benne's Best Meat","website":"www.bennesbest.com","facebook":"https://www.facebook.com/bennesbest","twitter":"","tags":"eggs fresh-vegetables poultry fowl red-meat non-poultry-meat"},{"type":"farm","street":"1804 Burmingham Rd","city":"Forsyth","state":"mo","zip":"65653","x":"-93.0777380","y":"36.6569689","name":"Beyond Eden","website":"vintagepoultry.com","facebook":"https://www.facebook.com/beyondeden","twitter":"","tags":"poultry fowl"},{"type":"farm","street":"120 E Fox Hollow Rd","city":"Ashland","state":"mo","zip":"65010","x":"-92.3456505","y":"38.7866936","name":"Blue Fox Farm","website":"http://www.bluefoxfood.com/","facebook":"https://www.facebook.com/pages/Blue-Fox-Farm/357267831061749","twitter":"","tags":"baked-goods canned preserved coffee tea cut-flowers dairy products eggs herbs fresh-fruits fresh-vegetables honey juices ciders maple-products mushrooms poultry fowl prepared-foods red-meat non-poultry-meat soap body-care wild-harvested forest-products wine spirits beer hard-cider"},{"type":"farm","street":"7226 Highway O","city":"Ash Grove","state":"mo","zip":"65604","x":"-93.638307","y":"37.173422","name":"Blue Silo Beef","website":"https://bluesilobeef.com/","facebook":"https://www.facebook.com/bluesilobeef","twitter":"","tags":"red-meat non-poultry-meat"},{"type":"farm","street":"324 Velvet Antler Road","city":"Camdenton","state":"mo","zip":"65020","x":"-92.8551303","y":"38.0903328","name":"Canyon Goat Company, Inc.","website":"http://www.canyongoat.com/index.html","facebook":"https://www.facebook.com/pages/Canyon-Goat-Company/218608414896707?sk=info","twitter":"","tags":"red-meat non-poultry-meat"},{"type":"farm","street":"199 Jackson St.","city":"Augusta ","state":"mo","zip":"63332","x":"-90.8878600","y":"38.5742400","name":"Centennial Farms and Orchard","website":"CENTENNIAL FARMS.BIZ","facebook":"","twitter":"","tags":"baked-goods bedding plants canned preserved herbs fresh-fruits fresh-vegetables honey soap body-care"},{"type":"farm","street":"13948 Highway 15","city":"Paris","state":"mo","zip":"65275","x":"-91.997360","y":"39.394888","name":"Davis Farm","website":"","facebook":"","twitter":"","tags":"grains flour red-meat non-poultry-meat"},{"type":"farm","street":"30305 Thrush Drive","city":"Richland","state":"mo","zip":"65556","x":"-92.4438987","y":"37.7770030","name":"Farm Market","website":"","facebook":"","twitter":"","tags":"bedding plants fresh-fruits fresh-vegetables"},{"type":"farm","street":"13906 Osage Valley Rd","city":"Boonville","state":"mo","zip":"65233","x":"-92.7573691","y":"38.8851101","name":"Fed From The Farm","website":"https://fedfromthefarm.com/","facebook":"https://www.facebook.com/boatrightfarms/","twitter":"","tags":"dairy products eggs poultry fowl red-meat non-poultry-meat"},{"type":"farm","street":"2096 Farm Road 1130","city":"Verona","state":"mo","zip":"65769","x":"-93.827266","y":"36.896851","name":"G's Orchard","website":"","facebook":"","twitter":"","tags":"fresh-fruits fresh-vegetables"},{"type":"farm","street":"P.O. Box 74","city":"Weston","state":"mo","zip":"64098","x":"-94.9016298","y":"39.4111092","name":"Green Dirt Farm, LLC","website":"","facebook":"https://www.facebook.com/greendirtfarm","twitter":"","tags":"dairy products red-meat non-poultry-meat"},{"type":"farm","street":"RR 71 Box 1168","city":"Wheatland","state":"mo","zip":"65779","x":"-93.383060","y":"37.993085","name":"Green Gate Family Farm LLC","website":"","facebook":"","twitter":"","tags":"cut-flowers eggs fresh-fruits fresh-vegetables mushrooms poultry fowl"},{"type":"farm","street":"4905 highway 5","city":"Hartville","state":"mo","zip":"65667","x":"-92.555292","y":"37.286090","name":"Greenhill Vineyard and Farm.  We sell grapes.","website":"www.greenhillgrapes.com","facebook":"","twitter":"","tags":"fresh-fruits"},{"type":"farm","street":"41903 e. 144th","city":"richmond","state":"mo","zip":"64085","x":"-93.963643","y":"39.350219","name":"haines farms","website":"","facebook":"www.facebook.com/hainesfarms","twitter":"","tags":"bedding plants crafts woodworking cut-flowers eggs herbs fresh-fruits fresh-vegetables nursery-stock nuts wild-harvested forest-products"},{"type":"farm","street":"160 county road 831","city":"Sikeston","state":"mo","zip":"63801","x":"-89.676996","y":"36.828947","name":"Hamra Farms","website":"","facebook":"Hamra Farms","twitter":"https://www.twitter.com/HamraFarms","tags":"canned preserved fresh-vegetables"},{"type":"farm","street":"3738 Highway 47","city":"Lonedell","state":"mo","zip":"63060","x":"-90.868656","y":"38.238180","name":"Hart Apiaries","website":"www.hartapiaries.com","facebook":"","twitter":"","tags":"fresh-fruits honey"},{"type":"farm","street":"4738 W. State Hwy 86","city":"Lampe","state":"mo","zip":"65681","x":"-93.495140","y":"36.509845","name":"Heritage Farm and Ranch","website":"http://www.heritageranch.co/","facebook":"https://www.facebook.com/HeritageRanchBB","twitter":"","tags":"canned preserved eggs herbs fresh-fruits fresh-vegetables red-meat non-poultry-meat"},{"type":"farm","street":"3663 N. Highway 94","city":"St. Charles","state":"mo","zip":"63301","x":"-90.470826","y":"38.832144","name":"Hermans Farm Orchard","website":"www.hermansfarmorchard.com","facebook":"https://www.facebook.com/pages/Hermans-Farm-Orchard/159616344096544","twitter":"","tags":"bedding plants canned preserved eggs herbs fresh-fruits fresh-vegetables honey juices ciders nursery-stock"},{"type":"farm","street":"434 Whispering Wind Lane","city":"Cape Girardeau","state":"mo","zip":"63701","x":"-89.494019","y":"37.371078","name":"Hinkebein Hills Farm","website":"","facebook":"https://www.facebook.com/hinkebeins?rf=110698638992813","twitter":"","tags":"eggs poultry fowl red-meat non-poultry-meat"},{"type":"farm","street":"26 NE 80th Street","city":"Spickard","state":"mo","zip":"64679","x":"-93.588959","y":"40.189456","name":"Homestead Hill Farm & Nursery","website":"homesteadhillfarming.com","facebook":"https://www.facebook.com/HomesteadHillFarmandNursery/","twitter":"","tags":"baked-goods bedding plants canned preserved crafts woodworking cut-flowers eggs herbs fresh-fruits fresh-vegetables nursery-stock soap body-care wild-harvested forest-products"},{"type":"farm","street":"2428 Texas Prairie Rd","city":"Bates City","state":"mo","zip":"64011","x":"-94.066232","y":"39.025235","name":"John & Linda Fruit and Berry Farm","website":"","facebook":"","twitter":"","tags":"cut-flowers fresh-fruits fresh-vegetables"},{"type":"farm","street":"5550 County Road 1820","city":"West Plains","state":"mo","zip":"65775","x":"-91.8615530","y":"36.8335309","name":"Jolliff Farm","website":"http://jollifffarm.wordpress.com/","facebook":"","twitter":"","tags":"fresh-fruits fresh-vegetables"},{"type":"farm","street":"8001 Bode Ferry Rd","city":"Jefferson City","state":"mo","zip":"65101","x":"-92.089989","y":"38.469585","name":"Lage Farms LLC","website":"lagefarms.com","facebook":"lagefarms.com","twitter":"","tags":"red-meat non-poultry-meat"},{"type":"farm","street":"11529 HWY NN","city":"Louisiana","state":"mo","zip":"63353","x":"-91.076797","y":"39.427775","name":"Lil' Sprouts Farm","website":"www.EarthSprouts.com","facebook":"Www.facebook.com/lilsproutsfarm","twitter":"","tags":"cut-flowers dry beans eggs herbs fresh-fruits fresh-vegetables grains flour mushrooms soap body-care wild-harvested forest-products"},{"type":"farm","street":"21507 Lost Branch Way","city":"Brashear","state":"mo","zip":"63533","x":"-92.4550740","y":"40.1729085","name":"Lost Branch Blueberry Farm","website":"www.lostbranchblueberries.com","facebook":"www.facebook.com/lostbranchblueberryfarm","twitter":"@pricefamilylbbf","tags":""},{"type":"farm","street":"12465 ST RT JJ","city":"West Plains","state":"mo","zip":"65775","x":"-91.901681","y":"36.591597","name":"Lucky Falling Star Ranch LLC","website":"www.luckyfallingstarranch.com ","facebook":"","twitter":"","tags":"eggs red-meat non-poultry-meat"},{"type":"farm","street":"603 South Main Street","city":"Salem","state":"mo","zip":"65560","x":"-91.535215","y":"37.638961","name":"Meramec Bison Farm, LLC","website":"www.meramecbison.com","facebook":"https://www.facebook.com/pages/Meramec-Bison-Farm-LLC/195576180525013","twitter":"","tags":""},{"type":"farm","street":"17819 Hwy UU","city":"Louisiana","state":"mo","zip":"63353","x":"-91.143758","y":"39.411628","name":"Meyer farm","website":"","facebook":"Meyer farm","twitter":"","tags":"cut-flowers herbs fresh-fruits fresh-vegetables honey prepared-foods"},{"type":"farm","street":"29286 State Highway C","city":"La Grange ","state":"mo","zip":"63448","x":"-91.591174","y":"40.048545","name":"Miles Farms","website":"","facebook":"www.facebook.com/MilesFarmsMarket","twitter":"https://twitter.com/Miles_Farms","tags":"baked-goods herbs fresh-fruits fresh-vegetables soap body-care"},{"type":"farm","street":"11425 Street Highway KK","city":"Marshfield","state":"mo","zip":"65706","x":"-92.927052","y":"37.294758","name":"Millers Berry Farm","website":"","facebook":"Millers Berry Farm","twitter":"","tags":"fresh-fruits"},{"type":"farm","street":"Rt. 81, Box 149","city":"Koshkonong","state":"mo","zip":"65692","x":"-91.6456994","y":"36.5958946","name":"Missouri's Best Beef Co-Op","website":"www.mobest beef.com","facebook":"","twitter":"","tags":""},{"type":"farm","street":"7470 Jakes Prairie Road","city":"Sullivan","state":"mo","zip":"63080","x":"-91.2978842","y":"38.2798417","name":"Northern Prairie Alpacas, LLC","website":"http://www.northernprairiealpacas.com/","facebook":"https://www.facebook.com/pages/Northern-Prairie-Alpacas-LLC/122810441106955?ref=bookmarks","twitter":"","tags":""},{"type":"farm","street":"1775 Old Hwy E","city":"Granby","state":"mo","zip":"64844","x":"-94.2634316","y":"36.9352568","name":"OakWoods Farm","website":"oakwoodsfarm.com","facebook":"https://www.facebook.com/pages/OakWoods-Farm/260088397378669","twitter":"https://twitter.com/oakwoodsfarm","tags":"bedding plants canned preserved eggs herbs fresh-fruits fresh-vegetables mushrooms"},{"type":"farm","street":"552 Lick Creek","city":"Leasburg","state":"mo","zip":"65535","x":"-91.308962","y":"38.090853","name":"Ozark Berry Farm","website":"Ozarkberryfarm.com","facebook":"https://www.facebook.com/Berries.Bugs.Blooms","twitter":"","tags":"fresh-fruits"},{"type":"farm","street":"30226 Holly Rd","city":"Pierce City","state":"mo","zip":"65723","x":"-94.0961713","y":"36.9292199","name":"Ozark Country Creations","website":"","facebook":"www.facebook.com/hatfieldtomatofarm","twitter":"","tags":"fresh-vegetables"},{"type":"farm","street":"12650 State Highway M","city":"Wright City","state":"mo","zip":"63390","x":"-91.012318","y":"38.785607","name":"Palme Acres Farms","website":"http://www.palmeacres.com","facebook":"","twitter":"","tags":"red-meat non-poultry-meat"},{"type":"farm","street":"8290 CR 1980","city":"West Plains","state":"mo","zip":"65775","x":"-91.738379","y":"36.846826","name":"Peace Valley Poultry","website":"www.freshchickenandturkey.com","facebook":"","twitter":"","tags":"pet-food poultry fowl soap body-care"},{"type":"farm","street":"3194 Oakwood Dr.","city":"Napoleon","state":"mo","zip":"64074","x":"-94.0485164","y":"39.0615522","name":"PlayHaven Farm LLC","website":"http://www.playhavenfarm.com/","facebook":"https://www.facebook.com/PlayHavenFarm","twitter":"","tags":"eggs poultry fowl red-meat non-poultry-meat"},{"type":"farm","street":"25717 FR 1168","city":"Eagle Rock ","state":"mo","zip":"65641","x":"-93.7812378","y":"36.5594726","name":"Prier Farms Grassfed #0389","website":"","facebook":"Prier Farms Grassfed #0389","twitter":"","tags":""},{"type":"farm","street":"416 Poplar Drive","city":"Highlandville","state":"mo","zip":"65669","x":"-93.317071","y":"36.901720","name":"Purple Gate Farm","website":"","facebook":"https://www.facebook.com/pages/Purple-Gate-Farm/566680560033305","twitter":"","tags":"eggs poultry fowl"},{"type":"farm","street":"624 Stringtown Rd","city":"Seymour","state":"mo","zip":"65746","x":"-92.7887619","y":"37.2556817","name":"Rachel's Goat & Chicken Farm","website":"http://www.rachelsgoatfarm.com/","facebook":"","twitter":"","tags":"eggs fresh-fruits fresh-vegetables poultry fowl red-meat non-poultry-meat soap body-care"},{"type":"farm","street":"21655 Hwy H","city":"Monett","state":"mo","zip":"65708","x":"-93.918396","y":"36.960386","name":"Rausch's Blueberries","website":"","facebook":"","twitter":"","tags":"fresh-fruits"},{"type":"farm","street":"37013 State Highway 25 South","city":"Malden ","state":"mo","zip":"63863","x":"-89.971274","y":"36.527500","name":"Sara's Produce","website":"","facebook":"https://www.facebook.com/SarasProduce","twitter":"","tags":"canned preserved eggs fresh-vegetables honey"},{"type":"farm","street":"1784 Doll Road","city":"Hermann","state":"mo","zip":"65041","x":"-91.4205244","y":"38.5912056","name":"Schneider Farms LLC","website":"www.schneiderfarmsllc.com","facebook":"https://www.facebook.com/Schneider-Farms-162860030399928","twitter":"","tags":"eggs poultry fowl red-meat non-poultry-meat"},{"type":"farm","street":"1068 S Metzletein Rd","city":"Clever","state":"mo","zip":"65631","x":"-93.4996849","y":"37.0244265","name":"Serendipity Acres, LLC","website":"","facebook":"https://www.facebook.com/Serendipityacresevans/","twitter":"","tags":"bedding plants canned preserved crafts woodworking cut-flowers eggs fresh-fruits fresh-vegetables honey maple-products mushrooms soap body-care"},{"type":"farm","street":"12780 Jantzen Ln","city":"Platte City","state":"mo","zip":"64079","x":"-94.845979","y":"39.321550","name":"Serendipity Farm & Orchard","website":"","facebook":"http://www.facebook.com/?ref=tn_tnmn#%21/SerendipityFarmOrchard","twitter":"","tags":"baked-goods canned preserved cut-flowers eggs fresh-fruits fresh-vegetables"},{"type":"farm","street":"4487 Elder Road Post Office Box 216","city":"Gray Summit","state":"mo","zip":"63089","x":"-90.862958","y":"38.492664","name":"Seven Gables Farm","website":"sevengablesfarm.com","facebook":"https://www.facebook.com/pages/Seven-Gables-Farm/618425231566963?sk=timeline","twitter":"","tags":"bedding plants canned preserved crafts woodworking cut-flowers dry beans eggs fresh-fruits fresh-vegetables mushrooms nursery-stock wine spirits beer hard-cider"},{"type":"farm","street":"8725 N Horseshoe Rd","city":"Dittmer","state":"mo","zip":"63023","x":"-90.7561350","y":"38.1978360","name":"Stone-Leady Farms","website":"www.stoneleadyfarms.com","facebook":"www.facebook.com/StoneLeadyFarms","twitter":"","tags":"dairy products fresh-vegetables red-meat non-poultry-meat soap body-care"},{"type":"farm","street":"19410 State Route O","city":"Rolla","state":"mo","zip":"65401","x":"-91.743907","y":"37.815275","name":"The Blue Hill Company, LLC","website":"www.thebluehillco.com","facebook":"https://www.facebook.com/TheBlueHillCo/","twitter":"","tags":"baked-goods canned preserved coffee tea honey nuts soap body-care"},{"type":"farm","street":"21505 Hwy OO","city":"Eolia","state":"mo","zip":"63344","x":"-96.690674","y":"36.544949","name":"Thistle Hill Plantation","website":"thistlehillplantation.com","facebook":"","twitter":"","tags":"crafts woodworking eggs juices ciders maple-products red-meat non-poultry-meat"},{"type":"farm","street":"15920 US highway 160","city":"Forsyth","state":"mo","zip":"65653","x":"-93.032275","y":"36.729878","name":"Tri-Lakes Orchards","website":"www.accounting-taxpros.com","facebook":"https://www.facebook.com/pages/Tri-Lakes-Orchards-LLC/279365858871273","twitter":"","tags":"fresh-vegetables"},{"type":"farm","street":"1002 Highway 19","city":"Hermann","state":"mo","zip":"65041","x":"-91.468241","y":"38.773117","name":"Wil farm","website":"wilfarm.org","facebook":"","twitter":"","tags":"bedding plants cut-flowers eggs fresh-fruits fresh-vegetables"},{"type":"farm","street":"3511 Hwy F","city":"New Melle","state":"mo","zip":"63365","x":"-90.878906","y":"38.708905","name":"Wind Ridge Farm","website":"Http://www.windridgefarm.net","facebook":"https://www.facebook.com/PickingUpdate?ref=ts","twitter":"HTTPS://www.twitter.com/Pickingupdate","tags":"fresh-vegetables"},{"type":"market","name":"Arnold Farmers Market","website":"https://www.arnoldmo.org/government/departments/parks-recreation/arnold-farmers-market/","facebook":"https://www.facebook.com/arnoldfarmersmarket/?ref=settings","twitter":"ArnoldFarmMarket","street":"2400 Bradley Beach Road","city":"Arnold","state":"mo","zip":"63010","x":"-90.353093","y":"38.453275","tags":"organic baked goods crafts flowers eggs herbs vegetables honey jams meat nuts plants poultry prepared-foods soap coffee beans fruits pet food wild"},{"type":"market","name":"Aurora Local Farmer's Market - Summer Market","website":"","facebook":"Aurora Local Farmers Market","twitter":"","street":"2031 S. Elliott Ave.","city":"Aurora","state":"mo","zip":"65605","x":"-93.7201867","y":"36.9489080","tags":"baked goods crafts flowers eggs herbs vegetables jams plants prepared-foods soap fruits wild"},{"type":"market","name":"Belton Farmers Market","website":"","facebook":"https://www.facebook.com/BeltonMoFarmersMarket/","twitter":"","street":"Memorial Park","city":"Belton ","state":"mo","zip":"64012","x":"-94.525252","y":"38.808556","tags":"baked goods crafts flowers eggs vegetables honey jams maple soap fruits"},{"type":"market","name":"Boonville Farmers Market Inc","website":"https://boonvillemofarmersmarket.weebly.com/","facebook":"@BoonvilleMOFarmersMarket","twitter":"@boonfarmmarket","street":"1931 Boone Village Shopping Center","city":"Boonville","state":"mo","zip":"65233","x":"-92.741591","y":"38.955643","tags":"baked goods crafts flowers eggs herbs vegetables honey jams meat plants poultry soap fruits mushrooms"},{"type":"market","name":"Cape Riverfront Market","website":"http://www.downtowncapegirardeau.com/cape-riverfront-market/","facebook":"https://www.facebook.com/CapeRiverfrontMarket","twitter":"","street":"35 S. Spanish St.","city":"Cape Girardeau","state":"mo","zip":"63701","x":"-89.519874","y":"37.302699","tags":"baked goods cheese crafts flowers eggs seafood herbs vegetables honey jams maple meat nuts plants prepared-foods soap trees coffee beans fruits mushrooms pet food"},{"type":"market","name":"Carrollton Farmers Market","website":"","facebook":"https://www.facebook.com/CarrolltonFarmersMarket","twitter":"","street":"Carrollton Uptown Square","city":"Carrollton","state":"mo","zip":"64633","x":"-93.496941","y":"39.358097","tags":"organic baked goods crafts eggs herbs vegetables honey jams plants prepared-foods fruits"},{"type":"market","name":"Columbia Farmers Market","website":"http://columbiafarmersmarket.org","facebook":"https://www.facebook.com/ColumbiaFarmersMarket","twitter":"https://twitter.com/comofarmers","street":"1769 West Ash Street","city":"Columbia","state":"mo","zip":"65203","x":"-92.364624","y":"38.958293","tags":"organic baked goods cheese crafts flowers eggs herbs vegetables honey jams meat nuts plants poultry prepared-foods soap trees coffee beans fruits juices mushrooms wild"},{"type":"market","name":"De Soto Farmers' Market","website":"http://www.gethealthydesoto.org","facebook":"https://www.facebook.com/cultivatingfoodandcommunity/","twitter":"","street":"520 N. Main Street","city":"DeSoto","state":"mo","zip":"63020","x":"-90.552184","y":"38.143961","tags":"baked goods crafts flowers eggs herbs vegetables honey jams meat plants poultry prepared-foods soap fruits"},{"type":"market","name":"Empire Market","website":"https://downtownjoplin.com/joplin-empire-market/","facebook":"https://www.facebook.com/JoplinEmpireMarket","twitter":"https://twitter.com/TheEmpireMarket","street":"931 E 4th St","city":"Joplin","state":"mo","zip":"64801","x":"-94.502691","y":"37.087883","tags":"organic baked goods crafts flowers eggs herbs vegetables honey jams meat plants poultry prepared-foods soap coffee fruits mushrooms"},{"type":"market","name":"Farmers Market of the Ozarks","website":"http://www.LoveYourFarmer.com","facebook":"https://www.facebook.com/FMOZARKS/","twitter":"https://twitter.com/FMOzarks","street":"2144 E Republic Rd","city":"Springfield","state":"mo","zip":"65804","x":"-93.255076","y":"37.136365","tags":"organic baked goods cheese crafts flowers eggs seafood herbs vegetables honey meat nuts plants poultry prepared-foods soap wine coffee fruits grains juices mushrooms wild"},{"type":"market","name":"Ferguson Farmers' Market","website":"http://fergusonfarmersmarket.com/","facebook":"https://www.facebook.com/FergusonFarmersMarket/","twitter":"","street":"Plaza 501, 501 S. Florissant Rd.","city":"Ferguson","state":"mo","zip":"63135","x":"-90.3027133","y":"38.7375795","tags":"organic baked goods crafts flowers eggs herbs vegetables honey plants prepared-foods soap wine coffee fruits grains"},{"type":"market","name":"Freeman Health System, West - Farmers Market","website":"","facebook":"","twitter":"","street":"1102 W 32nd Street","city":"Joplin","state":"mo","zip":"64801","x":"-94.5268459","y":"37.0526877","tags":"baked goods flowers eggs vegetables honey jams meat poultry fruits"},{"type":"market","name":"Gladstone Farmers' Market","website":"http://www.gladstone.mo.us/farmersmarket/","facebook":"https://www.facebook.com/pages/Gladstone-Farmers-Market/107406389284555?fref=ts","twitter":"","street":"602 NE 70th Street","city":"Gladstone","state":"mo","zip":"64118","x":"-94.5730016","y":"39.2214548","tags":"baked goods crafts flowers eggs herbs vegetables honey jams meat plants beans fruits"},{"type":"market","name":"Hillsboro Farmers Market","website":"http://www.kressfarm.org","facebook":"","twitter":"","street":"5137 Glade Chapel Road","city":"Hillsboro","state":"mo","zip":"63050","x":"-90.566655","y":"38.232278","tags":"baked goods vegetables honey jams meat plants poultry soap trees fruits juices mushrooms"},{"type":"market","name":"Holden MO Farmer's Market","website":"","facebook":"https://www.facebook.com/holdenmarket","twitter":"","street":"101 S Market St.","city":"Holden","state":"mo","zip":"64040","x":"-93.9908869","y":"38.7186566","tags":"baked goods crafts vegetables jams plants prepared-foods soap fruits pet food wild"},{"type":"market","name":"INDEPENDENCE UPTOWN MARKET","website":"http://independenceuptownmarket.com","facebook":"","twitter":"","street":"211 W. Truman Rd.","city":"Independence ","state":"mo","zip":"64050","x":"-94.418179","y":"39.093845","tags":"baked goods crafts flowers eggs vegetables honey jams meat nuts plants soap fruits"},{"type":"market","name":"Jackson (MO) Farmers Market","website":"","facebook":"Jackson Farmers Market","twitter":"","street":"252 E. Jackson Blvd.","city":"Jackson ","state":"mo","zip":"63755","x":"-89.6659726","y":"37.3778137","tags":"baked goods crafts eggs herbs vegetables honey jams maple nuts plants soap fruits"},{"type":"market","name":"Kirksville Kiwanis Farmers' Market","website":"","facebook":"Kirksville Kiwanis Farmers' Market","twitter":"","street":"100 North Elson Street","city":"Kirksville","state":"mo","zip":"63501","x":"-92.584293","y":"40.195114","tags":"baked goods crafts flowers eggs herbs vegetables honey jams meat plants poultry prepared-foods soap trees fruits juices"},{"type":"market","name":"Little Farm Store Market","website":"","facebook":"https://www.facebook.com/PleasantValleyFamilyFarm/","twitter":"","street":"520 Lucky Road","city":"Seymour","state":"mo","zip":"65746","x":"-92.680159","y":"37.118045","tags":"baked goods crafts flowers eggs herbs vegetables honey jams plants prepared-foods soap coffee fruits mushrooms"},{"type":"market","name":"Louisiana Community Betterment Farmer's Market","website":"","facebook":"Louisiana Community Betterment Farmers Market","twitter":"","street":"Sunset Park, Georgia Street","city":"Louisiana ","state":"mo","zip":"63353","x":"-91.062659","y":"39.441188","tags":"baked goods crafts flowers eggs herbs vegetables honey jams maple nuts plants prepared-foods soap fruits juices"},{"type":"market","name":"Midtown Farmers Market","website":"http://www.midwestfarmersmarkets.org/markets/midtown-farmers-market/","facebook":"https://www.facebook.com/Midtown-Farmers-Market-655879797806495/","twitter":"https://twitter.com/MidtownFmsMkt","street":"6655 Delmar Blvd, Back Lot","city":"University City","state":"mo","zip":"63130","x":"-90.307251","y":"38.656378","tags":"organic baked goods cheese crafts flowers eggs seafood herbs vegetables honey jams meat nuts plants poultry prepared-foods soap trees coffee fruits juices mushrooms pet food wild"},{"type":"market","name":"Neosho Farmers Market","website":"http://neoshofarmersmarket@gmail.com","facebook":"https://www.facebook.com/NeoshoFarmersMarket","twitter":"","street":"Spring & Jefferson St","city":"Downtown Neosho","state":"mo","zip":"64850","x":"-94.370028","y":"36.870009","tags":"baked goods cheese crafts flowers eggs herbs vegetables honey meat plants poultry prepared-foods soap trees coffee fruits juices"},{"type":"market","name":"Parkville Farmers' Market","website":"http://www.parkvillefarmersmarket.com","facebook":"https://www.facebook.com/pages/Parkville-Farmers-Market","twitter":"","street":"English Landing Park, off Hwy 9 in Parkville MO","city":"Parkville","state":"mo","zip":"","x":"-94.683086","y":"39.187828","tags":"baked goods crafts flowers eggs herbs vegetables honey jams meat plants prepared-foods soap coffee fruits wild"},{"type":"market","name":"Rogersville Farmer's Market","website":"","facebook":"https://www.facebook.com/rogersvillefriendsofthepark/","twitter":"","street":"270 County Line Road","city":"Rogersville","state":"mo","zip":"65741","x":"-93.066381","y":"37.115153","tags":"baked goods crafts flowers eggs herbs vegetables honey jams meat plants poultry prepared-foods soap trees coffee fruits juices mushrooms pet food"},{"type":"market","name":"Sedalia Area Farmers' Market","website":"http://www.sedaliaareafarmersmarket.com/","facebook":"https://www.facebook.com/SedaliaFarmersMarket/","twitter":"","street":"2233 W 16th St","city":"Sedalia, MO","state":"mo","zip":"65301","x":"-93.255481","y":"38.698011","tags":"baked goods crafts flowers eggs herbs vegetables honey jams meat plants poultry prepared-foods soap coffee beans fruits grains juices mushrooms pet food wild"},{"type":"market","name":"South St. Joseph Farmers Market at the Junction","website":"","facebook":"Southside Junction Farmers Market","twitter":"","street":"Lake & Illinois Avenues","city":"St. Joseph ","state":"mo","zip":"64504","x":"-94.865955","y":"39.718654","tags":"baked goods crafts flowers eggs herbs vegetables honey jams nuts plants prepared-foods soap fruits juices mushrooms pet food wild"},{"type":"market","name":"Vernon County Farmers Market","website":"","facebook":"Nevada Vernon County Farmers Market","twitter":"","street":"PO Box 873","city":"Nevada","state":"mo","zip":"64772","x":"-94.340102","y":"37.843772","tags":"baked goods flowers eggs herbs vegetables honey jams meat plants poultry soap fruits pet food"},{"type":"market","name":"West Plains Area Farmers' Market","website":"","facebook":"www.facebook.com/WestPlainsAreaFarmersMarket/","twitter":"","street":"1380 Bill Virdon Blvd.","city":"West Plains","state":"mo","zip":"65775","x":"-91.835774","y":"36.723987","tags":"organic baked goods crafts eggs herbs vegetables honey jams plants poultry soap fruits"}]
